package id.pras.jvmlang.bytecode;

/*
 * This file was generated by class id.pras.jvmlang.bytecode.Gen
 * which was executed by the gradle task GenJavaFiles
 * input path = /home/runner/work/jvmlang/jvmlang/ByteCode/sources/OpCode.txt
 */
// generated on Time: 16:33:51, Date: 02/10/2024 GMT+7
public final class OpCode {
  // for opCode this is the Size for instruction but for constant pool this is the size of the
  //constant pool tag
  public static final int SIZE = 1;
  public static final int NOP = 0x00;
  public static final String nop_ = "nop";
  public static final int ACONST_NULL = 0x01;
  public static final String aconst_null_ = "aconst_null";
  public static final int ICONST_M1 = 0x02;
  public static final String iconst_m1_ = "iconst_m1";
  public static final int ICONST_0 = 0x03;
  public static final String iconst_0_ = "iconst_0";
  public static final int ICONST_1 = 0x04;
  public static final String iconst_1_ = "iconst_1";
  public static final int ICONST_2 = 0x05;
  public static final String iconst_2_ = "iconst_2";
  public static final int ICONST_3 = 0x06;
  public static final String iconst_3_ = "iconst_3";
  public static final int ICONST_4 = 0x07;
  public static final String iconst_4_ = "iconst_4";
  public static final int ICONST_5 = 0x08;
  public static final String iconst_5_ = "iconst_5";
  public static final int LCONST_0 = 0x09;
  public static final String lconst_0_ = "lconst_0";
  public static final int LCONST_1 = 0x0A;
  public static final String lconst_1_ = "lconst_1";
  public static final int FCONST_0 = 0x0B;
  public static final String fconst_0_ = "fconst_0";
  public static final int FCONST_1 = 0x0C;
  public static final String fconst_1_ = "fconst_1";
  public static final int FCONST_2 = 0x0D;
  public static final String fconst_2_ = "fconst_2";
  public static final int DCONST_0 = 0x0E;
  public static final String dconst_0_ = "dconst_0";
  public static final int DCONST_1 = 0x0F;
  public static final String dconst_1_ = "dconst_1";
  public static final int BIPUSH = 0x10;
  public static final String bipush_ = "bipush";
  public static final int SIPUSH = 0x11;
  public static final String sipush_ = "sipush";
  public static final int LDC = 0x12;
  public static final String ldc_ = "ldc";
  public static final int LDC_W = 0x13;
  public static final String ldc_w_ = "ldc_w";
  public static final int LDC2_W = 0x14;
  public static final String ldc2_w_ = "ldc2_w";
  public static final int ILOAD = 0x15;
  public static final String iload_ = "iload";
  public static final int LLOAD = 0x16;
  public static final String lload_ = "lload";
  public static final int FLOAD = 0x17;
  public static final String fload_ = "fload";
  public static final int DLOAD = 0x18;
  public static final String dload_ = "dload";
  public static final int ALOAD = 0x19;
  public static final String aload_ = "aload";
  public static final int ILOAD_0 = 0x1A;
  public static final String iload_0_ = "iload_0";
  public static final int ILOAD_1 = 0x1B;
  public static final String iload_1_ = "iload_1";
  public static final int ILOAD_2 = 0x1C;
  public static final String iload_2_ = "iload_2";
  public static final int ILOAD_3 = 0x1D;
  public static final String iload_3_ = "iload_3";
  public static final int LLOAD_0 = 0x1E;
  public static final String lload_0_ = "lload_0";
  public static final int LLOAD_1 = 0x1F;
  public static final String lload_1_ = "lload_1";
  public static final int LLOAD_2 = 0x20;
  public static final String lload_2_ = "lload_2";
  public static final int LLOAD_3 = 0x21;
  public static final String lload_3_ = "lload_3";
  public static final int FLOAD_0 = 0x22;
  public static final String fload_0_ = "fload_0";
  public static final int FLOAD_1 = 0x23;
  public static final String fload_1_ = "fload_1";
  public static final int FLOAD_2 = 0x24;
  public static final String fload_2_ = "fload_2";
  public static final int FLOAD_3 = 0x25;
  public static final String fload_3_ = "fload_3";
  public static final int DLOAD_0 = 0x26;
  public static final String dload_0_ = "dload_0";
  public static final int DLOAD_1 = 0x27;
  public static final String dload_1_ = "dload_1";
  public static final int DLOAD_2 = 0x28;
  public static final String dload_2_ = "dload_2";
  public static final int DLOAD_3 = 0x29;
  public static final String dload_3_ = "dload_3";
  public static final int ALOAD_0 = 0x2A;
  public static final String aload_0_ = "aload_0";
  public static final int ALOAD_1 = 0x2B;
  public static final String aload_1_ = "aload_1";
  public static final int ALOAD_2 = 0x2C;
  public static final String aload_2_ = "aload_2";
  public static final int ALOAD_3 = 0x2D;
  public static final String aload_3_ = "aload_3";
  public static final int IALOAD = 0x2E;
  public static final String iaload_ = "iaload";
  public static final int LALOAD = 0x2F;
  public static final String laload_ = "laload";
  public static final int FALOAD = 0x30;
  public static final String faload_ = "faload";
  public static final int DALOAD = 0x31;
  public static final String daload_ = "daload";
  public static final int AALOAD = 0x32;
  public static final String aaload_ = "aaload";
  public static final int BALOAD = 0x33;
  public static final String baload_ = "baload";
  public static final int CALOAD = 0x34;
  public static final String caload_ = "caload";
  public static final int SALOAD = 0x35;
  public static final String saload_ = "saload";
  public static final int ISTORE = 0x36;
  public static final String istore_ = "istore";
  public static final int LSTORE = 0x37;
  public static final String lstore_ = "lstore";
  public static final int FSTORE = 0x38;
  public static final String fstore_ = "fstore";
  public static final int DSTORE = 0x39;
  public static final String dstore_ = "dstore";
  public static final int ASTORE = 0x3A;
  public static final String astore_ = "astore";
  public static final int ISTORE_0 = 0x3B;
  public static final String istore_0_ = "istore_0";
  public static final int ISTORE_1 = 0x3C;
  public static final String istore_1_ = "istore_1";
  public static final int ISTORE_2 = 0x3D;
  public static final String istore_2_ = "istore_2";
  public static final int ISTORE_3 = 0x3E;
  public static final String istore_3_ = "istore_3";
  public static final int LSTORE_0 = 0x3F;
  public static final String lstore_0_ = "lstore_0";
  public static final int LSTORE_1 = 0x40;
  public static final String lstore_1_ = "lstore_1";
  public static final int LSTORE_2 = 0x41;
  public static final String lstore_2_ = "lstore_2";
  public static final int LSTORE_3 = 0x42;
  public static final String lstore_3_ = "lstore_3";
  public static final int FSTORE_0 = 0x43;
  public static final String fstore_0_ = "fstore_0";
  public static final int FSTORE_1 = 0x44;
  public static final String fstore_1_ = "fstore_1";
  public static final int FSTORE_2 = 0x45;
  public static final String fstore_2_ = "fstore_2";
  public static final int FSTORE_3 = 0x46;
  public static final String fstore_3_ = "fstore_3";
  public static final int DSTORE_0 = 0x47;
  public static final String dstore_0_ = "dstore_0";
  public static final int DSTORE_1 = 0x48;
  public static final String dstore_1_ = "dstore_1";
  public static final int DSTORE_2 = 0x49;
  public static final String dstore_2_ = "dstore_2";
  public static final int DSTORE_3 = 0x4A;
  public static final String dstore_3_ = "dstore_3";
  public static final int ASTORE_0 = 0x4B;
  public static final String astore_0_ = "astore_0";
  public static final int ASTORE_1 = 0x4C;
  public static final String astore_1_ = "astore_1";
  public static final int ASTORE_2 = 0x4D;
  public static final String astore_2_ = "astore_2";
  public static final int ASTORE_3 = 0x4E;
  public static final String astore_3_ = "astore_3";
  public static final int IASTORE = 0x4F;
  public static final String iastore_ = "iastore";
  public static final int LASTORE = 0x50;
  public static final String lastore_ = "lastore";
  public static final int FASTORE = 0x51;
  public static final String fastore_ = "fastore";
  public static final int DASTORE = 0x52;
  public static final String dastore_ = "dastore";
  public static final int AASTORE = 0x53;
  public static final String aastore_ = "aastore";
  public static final int BASTORE = 0x54;
  public static final String bastore_ = "bastore";
  public static final int CASTORE = 0x55;
  public static final String castore_ = "castore";
  public static final int SASTORE = 0x56;
  public static final String sastore_ = "sastore";
  public static final int POP = 0x57;
  public static final String pop_ = "pop";
  public static final int POP2 = 0x58;
  public static final String pop2_ = "pop2";
  public static final int DUP = 0x59;
  public static final String dup_ = "dup";
  public static final int DUP_X1 = 0x5A;
  public static final String dup_x1_ = "dup_x1";
  public static final int DUP_X2 = 0x5B;
  public static final String dup_x2_ = "dup_x2";
  public static final int DUP2 = 0x5C;
  public static final String dup2_ = "dup2";
  public static final int DUP2_X1 = 0x5D;
  public static final String dup2_x1_ = "dup2_x1";
  public static final int DUP2_X2 = 0x5E;
  public static final String dup2_x2_ = "dup2_x2";
  public static final int SWAP = 0x5F;
  public static final String swap_ = "swap";
  public static final int IADD = 0x60;
  public static final String iadd_ = "iadd";
  public static final int LADD = 0x61;
  public static final String ladd_ = "ladd";
  public static final int FADD = 0x62;
  public static final String fadd_ = "fadd";
  public static final int DADD = 0x63;
  public static final String dadd_ = "dadd";
  public static final int ISUB = 0x64;
  public static final String isub_ = "isub";
  public static final int LSUB = 0x65;
  public static final String lsub_ = "lsub";
  public static final int FSUB = 0x66;
  public static final String fsub_ = "fsub";
  public static final int DSUB = 0x67;
  public static final String dsub_ = "dsub";
  public static final int IMUL = 0x68;
  public static final String imul_ = "imul";
  public static final int LMUL = 0x69;
  public static final String lmul_ = "lmul";
  public static final int FMUL = 0x6A;
  public static final String fmul_ = "fmul";
  public static final int DMUL = 0x6B;
  public static final String dmul_ = "dmul";
  public static final int IDIV = 0x6C;
  public static final String idiv_ = "idiv";
  public static final int LDIV = 0x6D;
  public static final String ldiv_ = "ldiv";
  public static final int FDIV = 0x6E;
  public static final String fdiv_ = "fdiv";
  public static final int DDIV = 0x6F;
  public static final String ddiv_ = "ddiv";
  public static final int IREM = 0x70;
  public static final String irem_ = "irem";
  public static final int LREM = 0x71;
  public static final String lrem_ = "lrem";
  public static final int FREM = 0x72;
  public static final String frem_ = "frem";
  public static final int DREM = 0x73;
  public static final String drem_ = "drem";
  public static final int INEG = 0x74;
  public static final String ineg_ = "ineg";
  public static final int LNEG = 0x75;
  public static final String lneg_ = "lneg";
  public static final int FNEG = 0x76;
  public static final String fneg_ = "fneg";
  public static final int DNEG = 0x77;
  public static final String dneg_ = "dneg";
  public static final int ISHL = 0x78;
  public static final String ishl_ = "ishl";
  public static final int LSHL = 0x79;
  public static final String lshl_ = "lshl";
  public static final int ISHR = 0x7A;
  public static final String ishr_ = "ishr";
  public static final int LSHR = 0x7B;
  public static final String lshr_ = "lshr";
  public static final int IUSHR = 0x7C;
  public static final String iushr_ = "iushr";
  public static final int LUSHR = 0x7D;
  public static final String lushr_ = "lushr";
  public static final int IAND = 0x7E;
  public static final String iand_ = "iand";
  public static final int LAND = 0x7F;
  public static final String land_ = "land";
  public static final int IOR = 0x80;
  public static final String ior_ = "ior";
  public static final int LOR = 0x81;
  public static final String lor_ = "lor";
  public static final int IXOR = 0x82;
  public static final String ixor_ = "ixor";
  public static final int LXOR = 0x83;
  public static final String lxor_ = "lxor";
  public static final int IINC = 0x84;
  public static final String iinc_ = "iinc";
  public static final int I2L = 0x85;
  public static final String i2l_ = "i2l";
  public static final int I2F = 0x86;
  public static final String i2f_ = "i2f";
  public static final int I2D = 0x87;
  public static final String i2d_ = "i2d";
  public static final int L2I = 0x88;
  public static final String l2i_ = "l2i";
  public static final int L2F = 0x89;
  public static final String l2f_ = "l2f";
  public static final int L2D = 0x8A;
  public static final String l2d_ = "l2d";
  public static final int F2I = 0x8B;
  public static final String f2i_ = "f2i";
  public static final int F2L = 0x8C;
  public static final String f2l_ = "f2l";
  public static final int F2D = 0x8D;
  public static final String f2d_ = "f2d";
  public static final int D2I = 0x8E;
  public static final String d2i_ = "d2i";
  public static final int D2L = 0x8F;
  public static final String d2l_ = "d2l";
  public static final int D2F = 0x90;
  public static final String d2f_ = "d2f";
  public static final int I2B = 0x91;
  public static final String i2b_ = "i2b";
  public static final int I2C = 0x92;
  public static final String i2c_ = "i2c";
  public static final int I2S = 0x93;
  public static final String i2s_ = "i2s";
  public static final int LCMP = 0x94;
  public static final String lcmp_ = "lcmp";
  public static final int FCMPL = 0x95;
  public static final String fcmpl_ = "fcmpl";
  public static final int FCMPG = 0x96;
  public static final String fcmpg_ = "fcmpg";
  public static final int DCMPL = 0x97;
  public static final String dcmpl_ = "dcmpl";
  public static final int DCMPG = 0x98;
  public static final String dcmpg_ = "dcmpg";
  public static final int IFEQ = 0x99;
  public static final String ifeq_ = "ifeq";
  public static final int IFNE = 0x9A;
  public static final String ifne_ = "ifne";
  public static final int IFLT = 0x9B;
  public static final String iflt_ = "iflt";
  public static final int IFGE = 0x9C;
  public static final String ifge_ = "ifge";
  public static final int IFGT = 0x9D;
  public static final String ifgt_ = "ifgt";
  public static final int IFLE = 0x9E;
  public static final String ifle_ = "ifle";
  public static final int IF_ICMPEQ = 0x9F;
  public static final String if_icmpeq_ = "if_icmpeq";
  public static final int IF_ICMPNE = 0xA0;
  public static final String if_icmpne_ = "if_icmpne";
  public static final int IF_ICMPLT = 0xA1;
  public static final String if_icmplt_ = "if_icmplt";
  public static final int IF_ICMPGE = 0xA2;
  public static final String if_icmpge_ = "if_icmpge";
  public static final int IF_ICMPGT = 0xA3;
  public static final String if_icmpgt_ = "if_icmpgt";
  public static final int IF_ICMPLE = 0xA4;
  public static final String if_icmple_ = "if_icmple";
  public static final int IF_ACMPEQ = 0xA5;
  public static final String if_acmpeq_ = "if_acmpeq";
  public static final int IF_ACMPNE = 0xA6;
  public static final String if_acmpne_ = "if_acmpne";
  public static final int GOTO = 0xA7;
  public static final String goto_ = "goto";
  public static final int JSR = 0xA8;
  public static final String jsr_ = "jsr";
  public static final int RET = 0xA9;
  public static final String ret_ = "ret";
  public static final int TABLESWITCH = 0xAA;
  public static final String tableswitch_ = "tableswitch";
  public static final int LOOKUPSWITCH = 0xAB;
  public static final String lookupswitch_ = "lookupswitch";
  public static final int IRETURN = 0xAC;
  public static final String ireturn_ = "ireturn";
  public static final int LRETURN = 0xAD;
  public static final String lreturn_ = "lreturn";
  public static final int FRETURN = 0xAE;
  public static final String freturn_ = "freturn";
  public static final int DRETURN = 0xAF;
  public static final String dreturn_ = "dreturn";
  public static final int ARETURN = 0xB0;
  public static final String areturn_ = "areturn";
  public static final int RETURN = 0xB1;
  public static final String return_ = "return";
  public static final int GETSTATIC = 0xB2;
  public static final String getstatic_ = "getstatic";
  public static final int PUTSTATIC = 0xB3;
  public static final String putstatic_ = "putstatic";
  public static final int GETFIELD = 0xB4;
  public static final String getfield_ = "getfield";
  public static final int PUTFIELD = 0xB5;
  public static final String putfield_ = "putfield";
  public static final int INVOKEVIRTUAL = 0xB6;
  public static final String invokevirtual_ = "invokevirtual";
  public static final int INVOKESPECIAL = 0xB7;
  public static final String invokespecial_ = "invokespecial";
  public static final int INVOKESTATIC = 0xB8;
  public static final String invokestatic_ = "invokestatic";
  public static final int INVOKEINTERFACE = 0xB9;
  public static final String invokeinterface_ = "invokeinterface";
  public static final int INVOKEDYNAMIC = 0xBA;
  public static final String invokedynamic_ = "invokedynamic";
  public static final int NEW = 0xBB;
  public static final String new_ = "new";
  public static final int NEWARRAY = 0xBC;
  public static final String newarray_ = "newarray";
  public static final int ANEWARRAY = 0xBD;
  public static final String anewarray_ = "anewarray";
  public static final int ARRAYLENGTH = 0xBE;
  public static final String arraylength_ = "arraylength";
  public static final int ATHROW = 0xBF;
  public static final String athrow_ = "athrow";
  public static final int CHECKCAST = 0xC0;
  public static final String checkcast_ = "checkcast";
  public static final int INSTANCEOF = 0xC1;
  public static final String instanceof_ = "instanceof";
  public static final int MONITORENTER = 0xC2;
  public static final String monitorenter_ = "monitorenter";
  public static final int MONITOREXIT = 0xC3;
  public static final String monitorexit_ = "monitorexit";
  public static final int WIDE = 0xC4;
  public static final String wide_ = "wide";
  public static final int MULTIANEWARRAY = 0xC5;
  public static final String multianewarray_ = "multianewarray";
  public static final int IFNULL = 0xC6;
  public static final String ifnull_ = "ifnull";
  public static final int IFNONNULL = 0xC7;
  public static final String ifnonnull_ = "ifnonnull";
  public static final int GOTO_W = 0xC8;
  public static final String goto_w_ = "goto_w";
  public static final int JSR_W = 0xC9;
  public static final String jsr_w_ = "jsr_w";
  public static final int BREAKPOINT = 0xCA;
  public static final String breakpoint_ = "breakpoint";
  public static final int IMPDEP1 = 0xFE;
  public static final String impdep1_ = "impdep1";
  public static final int IMPDEP2 = 0xFF;
  public static final String impdep2_ = "impdep2";
  public static final OpCode Nop = new OpCode(nop_, NOP);
  public static final OpCode Aconst_null = new OpCode(aconst_null_, ACONST_NULL);
  public static final OpCode Iconst_m1 = new OpCode(iconst_m1_, ICONST_M1);
  public static final OpCode Iconst_0 = new OpCode(iconst_0_, ICONST_0);
  public static final OpCode Iconst_1 = new OpCode(iconst_1_, ICONST_1);
  public static final OpCode Iconst_2 = new OpCode(iconst_2_, ICONST_2);
  public static final OpCode Iconst_3 = new OpCode(iconst_3_, ICONST_3);
  public static final OpCode Iconst_4 = new OpCode(iconst_4_, ICONST_4);
  public static final OpCode Iconst_5 = new OpCode(iconst_5_, ICONST_5);
  public static final OpCode Lconst_0 = new OpCode(lconst_0_, LCONST_0);
  public static final OpCode Lconst_1 = new OpCode(lconst_1_, LCONST_1);
  public static final OpCode Fconst_0 = new OpCode(fconst_0_, FCONST_0);
  public static final OpCode Fconst_1 = new OpCode(fconst_1_, FCONST_1);
  public static final OpCode Fconst_2 = new OpCode(fconst_2_, FCONST_2);
  public static final OpCode Dconst_0 = new OpCode(dconst_0_, DCONST_0);
  public static final OpCode Dconst_1 = new OpCode(dconst_1_, DCONST_1);
  public static final OpCode Bipush = new OpCode(bipush_, BIPUSH);
  public static final OpCode Sipush = new OpCode(sipush_, SIPUSH);
  public static final OpCode Ldc = new OpCode(ldc_, LDC);
  public static final OpCode Ldc_w = new OpCode(ldc_w_, LDC_W);
  public static final OpCode Ldc2_w = new OpCode(ldc2_w_, LDC2_W);
  public static final OpCode Iload = new OpCode(iload_, ILOAD);
  public static final OpCode Lload = new OpCode(lload_, LLOAD);
  public static final OpCode Fload = new OpCode(fload_, FLOAD);
  public static final OpCode Dload = new OpCode(dload_, DLOAD);
  public static final OpCode Aload = new OpCode(aload_, ALOAD);
  public static final OpCode Iload_0 = new OpCode(iload_0_, ILOAD_0);
  public static final OpCode Iload_1 = new OpCode(iload_1_, ILOAD_1);
  public static final OpCode Iload_2 = new OpCode(iload_2_, ILOAD_2);
  public static final OpCode Iload_3 = new OpCode(iload_3_, ILOAD_3);
  public static final OpCode Lload_0 = new OpCode(lload_0_, LLOAD_0);
  public static final OpCode Lload_1 = new OpCode(lload_1_, LLOAD_1);
  public static final OpCode Lload_2 = new OpCode(lload_2_, LLOAD_2);
  public static final OpCode Lload_3 = new OpCode(lload_3_, LLOAD_3);
  public static final OpCode Fload_0 = new OpCode(fload_0_, FLOAD_0);
  public static final OpCode Fload_1 = new OpCode(fload_1_, FLOAD_1);
  public static final OpCode Fload_2 = new OpCode(fload_2_, FLOAD_2);
  public static final OpCode Fload_3 = new OpCode(fload_3_, FLOAD_3);
  public static final OpCode Dload_0 = new OpCode(dload_0_, DLOAD_0);
  public static final OpCode Dload_1 = new OpCode(dload_1_, DLOAD_1);
  public static final OpCode Dload_2 = new OpCode(dload_2_, DLOAD_2);
  public static final OpCode Dload_3 = new OpCode(dload_3_, DLOAD_3);
  public static final OpCode Aload_0 = new OpCode(aload_0_, ALOAD_0);
  public static final OpCode Aload_1 = new OpCode(aload_1_, ALOAD_1);
  public static final OpCode Aload_2 = new OpCode(aload_2_, ALOAD_2);
  public static final OpCode Aload_3 = new OpCode(aload_3_, ALOAD_3);
  public static final OpCode Iaload = new OpCode(iaload_, IALOAD);
  public static final OpCode Laload = new OpCode(laload_, LALOAD);
  public static final OpCode Faload = new OpCode(faload_, FALOAD);
  public static final OpCode Daload = new OpCode(daload_, DALOAD);
  public static final OpCode Aaload = new OpCode(aaload_, AALOAD);
  public static final OpCode Baload = new OpCode(baload_, BALOAD);
  public static final OpCode Caload = new OpCode(caload_, CALOAD);
  public static final OpCode Saload = new OpCode(saload_, SALOAD);
  public static final OpCode Istore = new OpCode(istore_, ISTORE);
  public static final OpCode Lstore = new OpCode(lstore_, LSTORE);
  public static final OpCode Fstore = new OpCode(fstore_, FSTORE);
  public static final OpCode Dstore = new OpCode(dstore_, DSTORE);
  public static final OpCode Astore = new OpCode(astore_, ASTORE);
  public static final OpCode Istore_0 = new OpCode(istore_0_, ISTORE_0);
  public static final OpCode Istore_1 = new OpCode(istore_1_, ISTORE_1);
  public static final OpCode Istore_2 = new OpCode(istore_2_, ISTORE_2);
  public static final OpCode Istore_3 = new OpCode(istore_3_, ISTORE_3);
  public static final OpCode Lstore_0 = new OpCode(lstore_0_, LSTORE_0);
  public static final OpCode Lstore_1 = new OpCode(lstore_1_, LSTORE_1);
  public static final OpCode Lstore_2 = new OpCode(lstore_2_, LSTORE_2);
  public static final OpCode Lstore_3 = new OpCode(lstore_3_, LSTORE_3);
  public static final OpCode Fstore_0 = new OpCode(fstore_0_, FSTORE_0);
  public static final OpCode Fstore_1 = new OpCode(fstore_1_, FSTORE_1);
  public static final OpCode Fstore_2 = new OpCode(fstore_2_, FSTORE_2);
  public static final OpCode Fstore_3 = new OpCode(fstore_3_, FSTORE_3);
  public static final OpCode Dstore_0 = new OpCode(dstore_0_, DSTORE_0);
  public static final OpCode Dstore_1 = new OpCode(dstore_1_, DSTORE_1);
  public static final OpCode Dstore_2 = new OpCode(dstore_2_, DSTORE_2);
  public static final OpCode Dstore_3 = new OpCode(dstore_3_, DSTORE_3);
  public static final OpCode Astore_0 = new OpCode(astore_0_, ASTORE_0);
  public static final OpCode Astore_1 = new OpCode(astore_1_, ASTORE_1);
  public static final OpCode Astore_2 = new OpCode(astore_2_, ASTORE_2);
  public static final OpCode Astore_3 = new OpCode(astore_3_, ASTORE_3);
  public static final OpCode Iastore = new OpCode(iastore_, IASTORE);
  public static final OpCode Lastore = new OpCode(lastore_, LASTORE);
  public static final OpCode Fastore = new OpCode(fastore_, FASTORE);
  public static final OpCode Dastore = new OpCode(dastore_, DASTORE);
  public static final OpCode Aastore = new OpCode(aastore_, AASTORE);
  public static final OpCode Bastore = new OpCode(bastore_, BASTORE);
  public static final OpCode Castore = new OpCode(castore_, CASTORE);
  public static final OpCode Sastore = new OpCode(sastore_, SASTORE);
  public static final OpCode Pop = new OpCode(pop_, POP);
  public static final OpCode Pop2 = new OpCode(pop2_, POP2);
  public static final OpCode Dup = new OpCode(dup_, DUP);
  public static final OpCode Dup_x1 = new OpCode(dup_x1_, DUP_X1);
  public static final OpCode Dup_x2 = new OpCode(dup_x2_, DUP_X2);
  public static final OpCode Dup2 = new OpCode(dup2_, DUP2);
  public static final OpCode Dup2_x1 = new OpCode(dup2_x1_, DUP2_X1);
  public static final OpCode Dup2_x2 = new OpCode(dup2_x2_, DUP2_X2);
  public static final OpCode Swap = new OpCode(swap_, SWAP);
  public static final OpCode Iadd = new OpCode(iadd_, IADD);
  public static final OpCode Ladd = new OpCode(ladd_, LADD);
  public static final OpCode Fadd = new OpCode(fadd_, FADD);
  public static final OpCode Dadd = new OpCode(dadd_, DADD);
  public static final OpCode Isub = new OpCode(isub_, ISUB);
  public static final OpCode Lsub = new OpCode(lsub_, LSUB);
  public static final OpCode Fsub = new OpCode(fsub_, FSUB);
  public static final OpCode Dsub = new OpCode(dsub_, DSUB);
  public static final OpCode Imul = new OpCode(imul_, IMUL);
  public static final OpCode Lmul = new OpCode(lmul_, LMUL);
  public static final OpCode Fmul = new OpCode(fmul_, FMUL);
  public static final OpCode Dmul = new OpCode(dmul_, DMUL);
  public static final OpCode Idiv = new OpCode(idiv_, IDIV);
  public static final OpCode Ldiv = new OpCode(ldiv_, LDIV);
  public static final OpCode Fdiv = new OpCode(fdiv_, FDIV);
  public static final OpCode Ddiv = new OpCode(ddiv_, DDIV);
  public static final OpCode Irem = new OpCode(irem_, IREM);
  public static final OpCode Lrem = new OpCode(lrem_, LREM);
  public static final OpCode Frem = new OpCode(frem_, FREM);
  public static final OpCode Drem = new OpCode(drem_, DREM);
  public static final OpCode Ineg = new OpCode(ineg_, INEG);
  public static final OpCode Lneg = new OpCode(lneg_, LNEG);
  public static final OpCode Fneg = new OpCode(fneg_, FNEG);
  public static final OpCode Dneg = new OpCode(dneg_, DNEG);
  public static final OpCode Ishl = new OpCode(ishl_, ISHL);
  public static final OpCode Lshl = new OpCode(lshl_, LSHL);
  public static final OpCode Ishr = new OpCode(ishr_, ISHR);
  public static final OpCode Lshr = new OpCode(lshr_, LSHR);
  public static final OpCode Iushr = new OpCode(iushr_, IUSHR);
  public static final OpCode Lushr = new OpCode(lushr_, LUSHR);
  public static final OpCode Iand = new OpCode(iand_, IAND);
  public static final OpCode Land = new OpCode(land_, LAND);
  public static final OpCode Ior = new OpCode(ior_, IOR);
  public static final OpCode Lor = new OpCode(lor_, LOR);
  public static final OpCode Ixor = new OpCode(ixor_, IXOR);
  public static final OpCode Lxor = new OpCode(lxor_, LXOR);
  public static final OpCode Iinc = new OpCode(iinc_, IINC);
  public static final OpCode I2l = new OpCode(i2l_, I2L);
  public static final OpCode I2f = new OpCode(i2f_, I2F);
  public static final OpCode I2d = new OpCode(i2d_, I2D);
  public static final OpCode L2i = new OpCode(l2i_, L2I);
  public static final OpCode L2f = new OpCode(l2f_, L2F);
  public static final OpCode L2d = new OpCode(l2d_, L2D);
  public static final OpCode F2i = new OpCode(f2i_, F2I);
  public static final OpCode F2l = new OpCode(f2l_, F2L);
  public static final OpCode F2d = new OpCode(f2d_, F2D);
  public static final OpCode D2i = new OpCode(d2i_, D2I);
  public static final OpCode D2l = new OpCode(d2l_, D2L);
  public static final OpCode D2f = new OpCode(d2f_, D2F);
  public static final OpCode I2b = new OpCode(i2b_, I2B);
  public static final OpCode I2c = new OpCode(i2c_, I2C);
  public static final OpCode I2s = new OpCode(i2s_, I2S);
  public static final OpCode Lcmp = new OpCode(lcmp_, LCMP);
  public static final OpCode Fcmpl = new OpCode(fcmpl_, FCMPL);
  public static final OpCode Fcmpg = new OpCode(fcmpg_, FCMPG);
  public static final OpCode Dcmpl = new OpCode(dcmpl_, DCMPL);
  public static final OpCode Dcmpg = new OpCode(dcmpg_, DCMPG);
  public static final OpCode Ifeq = new OpCode(ifeq_, IFEQ);
  public static final OpCode Ifne = new OpCode(ifne_, IFNE);
  public static final OpCode Iflt = new OpCode(iflt_, IFLT);
  public static final OpCode Ifge = new OpCode(ifge_, IFGE);
  public static final OpCode Ifgt = new OpCode(ifgt_, IFGT);
  public static final OpCode Ifle = new OpCode(ifle_, IFLE);
  public static final OpCode If_icmpeq = new OpCode(if_icmpeq_, IF_ICMPEQ);
  public static final OpCode If_icmpne = new OpCode(if_icmpne_, IF_ICMPNE);
  public static final OpCode If_icmplt = new OpCode(if_icmplt_, IF_ICMPLT);
  public static final OpCode If_icmpge = new OpCode(if_icmpge_, IF_ICMPGE);
  public static final OpCode If_icmpgt = new OpCode(if_icmpgt_, IF_ICMPGT);
  public static final OpCode If_icmple = new OpCode(if_icmple_, IF_ICMPLE);
  public static final OpCode If_acmpeq = new OpCode(if_acmpeq_, IF_ACMPEQ);
  public static final OpCode If_acmpne = new OpCode(if_acmpne_, IF_ACMPNE);
  public static final OpCode Goto = new OpCode(goto_, GOTO);
  public static final OpCode Jsr = new OpCode(jsr_, JSR);
  public static final OpCode Ret = new OpCode(ret_, RET);
  public static final OpCode Tableswitch = new OpCode(tableswitch_, TABLESWITCH);
  public static final OpCode Lookupswitch = new OpCode(lookupswitch_, LOOKUPSWITCH);
  public static final OpCode Ireturn = new OpCode(ireturn_, IRETURN);
  public static final OpCode Lreturn = new OpCode(lreturn_, LRETURN);
  public static final OpCode Freturn = new OpCode(freturn_, FRETURN);
  public static final OpCode Dreturn = new OpCode(dreturn_, DRETURN);
  public static final OpCode Areturn = new OpCode(areturn_, ARETURN);
  public static final OpCode Return = new OpCode(return_, RETURN);
  public static final OpCode Getstatic = new OpCode(getstatic_, GETSTATIC);
  public static final OpCode Putstatic = new OpCode(putstatic_, PUTSTATIC);
  public static final OpCode Getfield = new OpCode(getfield_, GETFIELD);
  public static final OpCode Putfield = new OpCode(putfield_, PUTFIELD);
  public static final OpCode Invokevirtual = new OpCode(invokevirtual_, INVOKEVIRTUAL);
  public static final OpCode Invokespecial = new OpCode(invokespecial_, INVOKESPECIAL);
  public static final OpCode Invokestatic = new OpCode(invokestatic_, INVOKESTATIC);
  public static final OpCode Invokeinterface = new OpCode(invokeinterface_, INVOKEINTERFACE);
  public static final OpCode Invokedynamic = new OpCode(invokedynamic_, INVOKEDYNAMIC);
  public static final OpCode New = new OpCode(new_, NEW);
  public static final OpCode Newarray = new OpCode(newarray_, NEWARRAY);
  public static final OpCode Anewarray = new OpCode(anewarray_, ANEWARRAY);
  public static final OpCode Arraylength = new OpCode(arraylength_, ARRAYLENGTH);
  public static final OpCode Athrow = new OpCode(athrow_, ATHROW);
  public static final OpCode Checkcast = new OpCode(checkcast_, CHECKCAST);
  public static final OpCode Instanceof = new OpCode(instanceof_, INSTANCEOF);
  public static final OpCode Monitorenter = new OpCode(monitorenter_, MONITORENTER);
  public static final OpCode Monitorexit = new OpCode(monitorexit_, MONITOREXIT);
  public static final OpCode Wide = new OpCode(wide_, WIDE);
  public static final OpCode Multianewarray = new OpCode(multianewarray_, MULTIANEWARRAY);
  public static final OpCode Ifnull = new OpCode(ifnull_, IFNULL);
  public static final OpCode Ifnonnull = new OpCode(ifnonnull_, IFNONNULL);
  public static final OpCode Goto_w = new OpCode(goto_w_, GOTO_W);
  public static final OpCode Jsr_w = new OpCode(jsr_w_, JSR_W);
  public static final OpCode Breakpoint = new OpCode(breakpoint_, BREAKPOINT);
  public static final OpCode Impdep1 = new OpCode(impdep1_, IMPDEP1);
  public static final OpCode Impdep2 = new OpCode(impdep2_, IMPDEP2);
  private String name;
  private int code;

  private OpCode(String name, int code){
    this.name=name;
    this.code=code;
  }
  public String getName() {
    return this.name;
  }
  public int getCode() {
    return this.code;
  }

  private OpCode(){}
}
