//digenerasi ulang oleh id.pras.jvmlang.GenJavadocComment pada Time: 03:06:09, Date: 03/10/2024 GMT +7
package id.pras.jvmlang.bytecode;

/**
 * Kelas {@code OpCode} dihasilkan oleh kelas id.pras.jvmlang.bytecode.Gen
 * yang dieksekusi dari gradle task GenJavaFiles
 */
// digenerasi pada Time: 03:06:09, Date: 03/10/2024 GMT+7
public final class OpCode {
  /** {@value #SIZE} */
  public static final int SIZE = 1;
  /** {@value #NOP} */
  public static final int NOP = 0x00;
  /** {@value #nop_} */
  public static final String nop_ = "nop";
  /** {@value #ACONST_NULL} */
  public static final int ACONST_NULL = 0x01;
  /** {@value #aconst_null_} */
  public static final String aconst_null_ = "aconst_null";
  /** {@value #ICONST_M1} */
  public static final int ICONST_M1 = 0x02;
  /** {@value #iconst_m1_} */
  public static final String iconst_m1_ = "iconst_m1";
  /** {@value #ICONST_0} */
  public static final int ICONST_0 = 0x03;
  /** {@value #iconst_0_} */
  public static final String iconst_0_ = "iconst_0";
  /** {@value #ICONST_1} */
  public static final int ICONST_1 = 0x04;
  /** {@value #iconst_1_} */
  public static final String iconst_1_ = "iconst_1";
  /** {@value #ICONST_2} */
  public static final int ICONST_2 = 0x05;
  /** {@value #iconst_2_} */
  public static final String iconst_2_ = "iconst_2";
  /** {@value #ICONST_3} */
  public static final int ICONST_3 = 0x06;
  /** {@value #iconst_3_} */
  public static final String iconst_3_ = "iconst_3";
  /** {@value #ICONST_4} */
  public static final int ICONST_4 = 0x07;
  /** {@value #iconst_4_} */
  public static final String iconst_4_ = "iconst_4";
  /** {@value #ICONST_5} */
  public static final int ICONST_5 = 0x08;
  /** {@value #iconst_5_} */
  public static final String iconst_5_ = "iconst_5";
  /** {@value #LCONST_0} */
  public static final int LCONST_0 = 0x09;
  /** {@value #lconst_0_} */
  public static final String lconst_0_ = "lconst_0";
  /** {@value #LCONST_1} */
  public static final int LCONST_1 = 0x0A;
  /** {@value #lconst_1_} */
  public static final String lconst_1_ = "lconst_1";
  /** {@value #FCONST_0} */
  public static final int FCONST_0 = 0x0B;
  /** {@value #fconst_0_} */
  public static final String fconst_0_ = "fconst_0";
  /** {@value #FCONST_1} */
  public static final int FCONST_1 = 0x0C;
  /** {@value #fconst_1_} */
  public static final String fconst_1_ = "fconst_1";
  /** {@value #FCONST_2} */
  public static final int FCONST_2 = 0x0D;
  /** {@value #fconst_2_} */
  public static final String fconst_2_ = "fconst_2";
  /** {@value #DCONST_0} */
  public static final int DCONST_0 = 0x0E;
  /** {@value #dconst_0_} */
  public static final String dconst_0_ = "dconst_0";
  /** {@value #DCONST_1} */
  public static final int DCONST_1 = 0x0F;
  /** {@value #dconst_1_} */
  public static final String dconst_1_ = "dconst_1";
  /** {@value #BIPUSH} */
  public static final int BIPUSH = 0x10;
  /** {@value #bipush_} */
  public static final String bipush_ = "bipush";
  /** {@value #SIPUSH} */
  public static final int SIPUSH = 0x11;
  /** {@value #sipush_} */
  public static final String sipush_ = "sipush";
  /** {@value #LDC} */
  public static final int LDC = 0x12;
  /** {@value #ldc_} */
  public static final String ldc_ = "ldc";
  /** {@value #LDC_W} */
  public static final int LDC_W = 0x13;
  /** {@value #ldc_w_} */
  public static final String ldc_w_ = "ldc_w";
  /** {@value #LDC2_W} */
  public static final int LDC2_W = 0x14;
  /** {@value #ldc2_w_} */
  public static final String ldc2_w_ = "ldc2_w";
  /** {@value #ILOAD} */
  public static final int ILOAD = 0x15;
  /** {@value #iload_} */
  public static final String iload_ = "iload";
  /** {@value #LLOAD} */
  public static final int LLOAD = 0x16;
  /** {@value #lload_} */
  public static final String lload_ = "lload";
  /** {@value #FLOAD} */
  public static final int FLOAD = 0x17;
  /** {@value #fload_} */
  public static final String fload_ = "fload";
  /** {@value #DLOAD} */
  public static final int DLOAD = 0x18;
  /** {@value #dload_} */
  public static final String dload_ = "dload";
  /** {@value #ALOAD} */
  public static final int ALOAD = 0x19;
  /** {@value #aload_} */
  public static final String aload_ = "aload";
  /** {@value #ILOAD_0} */
  public static final int ILOAD_0 = 0x1A;
  /** {@value #iload_0_} */
  public static final String iload_0_ = "iload_0";
  /** {@value #ILOAD_1} */
  public static final int ILOAD_1 = 0x1B;
  /** {@value #iload_1_} */
  public static final String iload_1_ = "iload_1";
  /** {@value #ILOAD_2} */
  public static final int ILOAD_2 = 0x1C;
  /** {@value #iload_2_} */
  public static final String iload_2_ = "iload_2";
  /** {@value #ILOAD_3} */
  public static final int ILOAD_3 = 0x1D;
  /** {@value #iload_3_} */
  public static final String iload_3_ = "iload_3";
  /** {@value #LLOAD_0} */
  public static final int LLOAD_0 = 0x1E;
  /** {@value #lload_0_} */
  public static final String lload_0_ = "lload_0";
  /** {@value #LLOAD_1} */
  public static final int LLOAD_1 = 0x1F;
  /** {@value #lload_1_} */
  public static final String lload_1_ = "lload_1";
  /** {@value #LLOAD_2} */
  public static final int LLOAD_2 = 0x20;
  /** {@value #lload_2_} */
  public static final String lload_2_ = "lload_2";
  /** {@value #LLOAD_3} */
  public static final int LLOAD_3 = 0x21;
  /** {@value #lload_3_} */
  public static final String lload_3_ = "lload_3";
  /** {@value #FLOAD_0} */
  public static final int FLOAD_0 = 0x22;
  /** {@value #fload_0_} */
  public static final String fload_0_ = "fload_0";
  /** {@value #FLOAD_1} */
  public static final int FLOAD_1 = 0x23;
  /** {@value #fload_1_} */
  public static final String fload_1_ = "fload_1";
  /** {@value #FLOAD_2} */
  public static final int FLOAD_2 = 0x24;
  /** {@value #fload_2_} */
  public static final String fload_2_ = "fload_2";
  /** {@value #FLOAD_3} */
  public static final int FLOAD_3 = 0x25;
  /** {@value #fload_3_} */
  public static final String fload_3_ = "fload_3";
  /** {@value #DLOAD_0} */
  public static final int DLOAD_0 = 0x26;
  /** {@value #dload_0_} */
  public static final String dload_0_ = "dload_0";
  /** {@value #DLOAD_1} */
  public static final int DLOAD_1 = 0x27;
  /** {@value #dload_1_} */
  public static final String dload_1_ = "dload_1";
  /** {@value #DLOAD_2} */
  public static final int DLOAD_2 = 0x28;
  /** {@value #dload_2_} */
  public static final String dload_2_ = "dload_2";
  /** {@value #DLOAD_3} */
  public static final int DLOAD_3 = 0x29;
  /** {@value #dload_3_} */
  public static final String dload_3_ = "dload_3";
  /** {@value #ALOAD_0} */
  public static final int ALOAD_0 = 0x2A;
  /** {@value #aload_0_} */
  public static final String aload_0_ = "aload_0";
  /** {@value #ALOAD_1} */
  public static final int ALOAD_1 = 0x2B;
  /** {@value #aload_1_} */
  public static final String aload_1_ = "aload_1";
  /** {@value #ALOAD_2} */
  public static final int ALOAD_2 = 0x2C;
  /** {@value #aload_2_} */
  public static final String aload_2_ = "aload_2";
  /** {@value #ALOAD_3} */
  public static final int ALOAD_3 = 0x2D;
  /** {@value #aload_3_} */
  public static final String aload_3_ = "aload_3";
  /** {@value #IALOAD} */
  public static final int IALOAD = 0x2E;
  /** {@value #iaload_} */
  public static final String iaload_ = "iaload";
  /** {@value #LALOAD} */
  public static final int LALOAD = 0x2F;
  /** {@value #laload_} */
  public static final String laload_ = "laload";
  /** {@value #FALOAD} */
  public static final int FALOAD = 0x30;
  /** {@value #faload_} */
  public static final String faload_ = "faload";
  /** {@value #DALOAD} */
  public static final int DALOAD = 0x31;
  /** {@value #daload_} */
  public static final String daload_ = "daload";
  /** {@value #AALOAD} */
  public static final int AALOAD = 0x32;
  /** {@value #aaload_} */
  public static final String aaload_ = "aaload";
  /** {@value #BALOAD} */
  public static final int BALOAD = 0x33;
  /** {@value #baload_} */
  public static final String baload_ = "baload";
  /** {@value #CALOAD} */
  public static final int CALOAD = 0x34;
  /** {@value #caload_} */
  public static final String caload_ = "caload";
  /** {@value #SALOAD} */
  public static final int SALOAD = 0x35;
  /** {@value #saload_} */
  public static final String saload_ = "saload";
  /** {@value #ISTORE} */
  public static final int ISTORE = 0x36;
  /** {@value #istore_} */
  public static final String istore_ = "istore";
  /** {@value #LSTORE} */
  public static final int LSTORE = 0x37;
  /** {@value #lstore_} */
  public static final String lstore_ = "lstore";
  /** {@value #FSTORE} */
  public static final int FSTORE = 0x38;
  /** {@value #fstore_} */
  public static final String fstore_ = "fstore";
  /** {@value #DSTORE} */
  public static final int DSTORE = 0x39;
  /** {@value #dstore_} */
  public static final String dstore_ = "dstore";
  /** {@value #ASTORE} */
  public static final int ASTORE = 0x3A;
  /** {@value #astore_} */
  public static final String astore_ = "astore";
  /** {@value #ISTORE_0} */
  public static final int ISTORE_0 = 0x3B;
  /** {@value #istore_0_} */
  public static final String istore_0_ = "istore_0";
  /** {@value #ISTORE_1} */
  public static final int ISTORE_1 = 0x3C;
  /** {@value #istore_1_} */
  public static final String istore_1_ = "istore_1";
  /** {@value #ISTORE_2} */
  public static final int ISTORE_2 = 0x3D;
  /** {@value #istore_2_} */
  public static final String istore_2_ = "istore_2";
  /** {@value #ISTORE_3} */
  public static final int ISTORE_3 = 0x3E;
  /** {@value #istore_3_} */
  public static final String istore_3_ = "istore_3";
  /** {@value #LSTORE_0} */
  public static final int LSTORE_0 = 0x3F;
  /** {@value #lstore_0_} */
  public static final String lstore_0_ = "lstore_0";
  /** {@value #LSTORE_1} */
  public static final int LSTORE_1 = 0x40;
  /** {@value #lstore_1_} */
  public static final String lstore_1_ = "lstore_1";
  /** {@value #LSTORE_2} */
  public static final int LSTORE_2 = 0x41;
  /** {@value #lstore_2_} */
  public static final String lstore_2_ = "lstore_2";
  /** {@value #LSTORE_3} */
  public static final int LSTORE_3 = 0x42;
  /** {@value #lstore_3_} */
  public static final String lstore_3_ = "lstore_3";
  /** {@value #FSTORE_0} */
  public static final int FSTORE_0 = 0x43;
  /** {@value #fstore_0_} */
  public static final String fstore_0_ = "fstore_0";
  /** {@value #FSTORE_1} */
  public static final int FSTORE_1 = 0x44;
  /** {@value #fstore_1_} */
  public static final String fstore_1_ = "fstore_1";
  /** {@value #FSTORE_2} */
  public static final int FSTORE_2 = 0x45;
  /** {@value #fstore_2_} */
  public static final String fstore_2_ = "fstore_2";
  /** {@value #FSTORE_3} */
  public static final int FSTORE_3 = 0x46;
  /** {@value #fstore_3_} */
  public static final String fstore_3_ = "fstore_3";
  /** {@value #DSTORE_0} */
  public static final int DSTORE_0 = 0x47;
  /** {@value #dstore_0_} */
  public static final String dstore_0_ = "dstore_0";
  /** {@value #DSTORE_1} */
  public static final int DSTORE_1 = 0x48;
  /** {@value #dstore_1_} */
  public static final String dstore_1_ = "dstore_1";
  /** {@value #DSTORE_2} */
  public static final int DSTORE_2 = 0x49;
  /** {@value #dstore_2_} */
  public static final String dstore_2_ = "dstore_2";
  /** {@value #DSTORE_3} */
  public static final int DSTORE_3 = 0x4A;
  /** {@value #dstore_3_} */
  public static final String dstore_3_ = "dstore_3";
  /** {@value #ASTORE_0} */
  public static final int ASTORE_0 = 0x4B;
  /** {@value #astore_0_} */
  public static final String astore_0_ = "astore_0";
  /** {@value #ASTORE_1} */
  public static final int ASTORE_1 = 0x4C;
  /** {@value #astore_1_} */
  public static final String astore_1_ = "astore_1";
  /** {@value #ASTORE_2} */
  public static final int ASTORE_2 = 0x4D;
  /** {@value #astore_2_} */
  public static final String astore_2_ = "astore_2";
  /** {@value #ASTORE_3} */
  public static final int ASTORE_3 = 0x4E;
  /** {@value #astore_3_} */
  public static final String astore_3_ = "astore_3";
  /** {@value #IASTORE} */
  public static final int IASTORE = 0x4F;
  /** {@value #iastore_} */
  public static final String iastore_ = "iastore";
  /** {@value #LASTORE} */
  public static final int LASTORE = 0x50;
  /** {@value #lastore_} */
  public static final String lastore_ = "lastore";
  /** {@value #FASTORE} */
  public static final int FASTORE = 0x51;
  /** {@value #fastore_} */
  public static final String fastore_ = "fastore";
  /** {@value #DASTORE} */
  public static final int DASTORE = 0x52;
  /** {@value #dastore_} */
  public static final String dastore_ = "dastore";
  /** {@value #AASTORE} */
  public static final int AASTORE = 0x53;
  /** {@value #aastore_} */
  public static final String aastore_ = "aastore";
  /** {@value #BASTORE} */
  public static final int BASTORE = 0x54;
  /** {@value #bastore_} */
  public static final String bastore_ = "bastore";
  /** {@value #CASTORE} */
  public static final int CASTORE = 0x55;
  /** {@value #castore_} */
  public static final String castore_ = "castore";
  /** {@value #SASTORE} */
  public static final int SASTORE = 0x56;
  /** {@value #sastore_} */
  public static final String sastore_ = "sastore";
  /** {@value #POP} */
  public static final int POP = 0x57;
  /** {@value #pop_} */
  public static final String pop_ = "pop";
  /** {@value #POP2} */
  public static final int POP2 = 0x58;
  /** {@value #pop2_} */
  public static final String pop2_ = "pop2";
  /** {@value #DUP} */
  public static final int DUP = 0x59;
  /** {@value #dup_} */
  public static final String dup_ = "dup";
  /** {@value #DUP_X1} */
  public static final int DUP_X1 = 0x5A;
  /** {@value #dup_x1_} */
  public static final String dup_x1_ = "dup_x1";
  /** {@value #DUP_X2} */
  public static final int DUP_X2 = 0x5B;
  /** {@value #dup_x2_} */
  public static final String dup_x2_ = "dup_x2";
  /** {@value #DUP2} */
  public static final int DUP2 = 0x5C;
  /** {@value #dup2_} */
  public static final String dup2_ = "dup2";
  /** {@value #DUP2_X1} */
  public static final int DUP2_X1 = 0x5D;
  /** {@value #dup2_x1_} */
  public static final String dup2_x1_ = "dup2_x1";
  /** {@value #DUP2_X2} */
  public static final int DUP2_X2 = 0x5E;
  /** {@value #dup2_x2_} */
  public static final String dup2_x2_ = "dup2_x2";
  /** {@value #SWAP} */
  public static final int SWAP = 0x5F;
  /** {@value #swap_} */
  public static final String swap_ = "swap";
  /** {@value #IADD} */
  public static final int IADD = 0x60;
  /** {@value #iadd_} */
  public static final String iadd_ = "iadd";
  /** {@value #LADD} */
  public static final int LADD = 0x61;
  /** {@value #ladd_} */
  public static final String ladd_ = "ladd";
  /** {@value #FADD} */
  public static final int FADD = 0x62;
  /** {@value #fadd_} */
  public static final String fadd_ = "fadd";
  /** {@value #DADD} */
  public static final int DADD = 0x63;
  /** {@value #dadd_} */
  public static final String dadd_ = "dadd";
  /** {@value #ISUB} */
  public static final int ISUB = 0x64;
  /** {@value #isub_} */
  public static final String isub_ = "isub";
  /** {@value #LSUB} */
  public static final int LSUB = 0x65;
  /** {@value #lsub_} */
  public static final String lsub_ = "lsub";
  /** {@value #FSUB} */
  public static final int FSUB = 0x66;
  /** {@value #fsub_} */
  public static final String fsub_ = "fsub";
  /** {@value #DSUB} */
  public static final int DSUB = 0x67;
  /** {@value #dsub_} */
  public static final String dsub_ = "dsub";
  /** {@value #IMUL} */
  public static final int IMUL = 0x68;
  /** {@value #imul_} */
  public static final String imul_ = "imul";
  /** {@value #LMUL} */
  public static final int LMUL = 0x69;
  /** {@value #lmul_} */
  public static final String lmul_ = "lmul";
  /** {@value #FMUL} */
  public static final int FMUL = 0x6A;
  /** {@value #fmul_} */
  public static final String fmul_ = "fmul";
  /** {@value #DMUL} */
  public static final int DMUL = 0x6B;
  /** {@value #dmul_} */
  public static final String dmul_ = "dmul";
  /** {@value #IDIV} */
  public static final int IDIV = 0x6C;
  /** {@value #idiv_} */
  public static final String idiv_ = "idiv";
  /** {@value #LDIV} */
  public static final int LDIV = 0x6D;
  /** {@value #ldiv_} */
  public static final String ldiv_ = "ldiv";
  /** {@value #FDIV} */
  public static final int FDIV = 0x6E;
  /** {@value #fdiv_} */
  public static final String fdiv_ = "fdiv";
  /** {@value #DDIV} */
  public static final int DDIV = 0x6F;
  /** {@value #ddiv_} */
  public static final String ddiv_ = "ddiv";
  /** {@value #IREM} */
  public static final int IREM = 0x70;
  /** {@value #irem_} */
  public static final String irem_ = "irem";
  /** {@value #LREM} */
  public static final int LREM = 0x71;
  /** {@value #lrem_} */
  public static final String lrem_ = "lrem";
  /** {@value #FREM} */
  public static final int FREM = 0x72;
  /** {@value #frem_} */
  public static final String frem_ = "frem";
  /** {@value #DREM} */
  public static final int DREM = 0x73;
  /** {@value #drem_} */
  public static final String drem_ = "drem";
  /** {@value #INEG} */
  public static final int INEG = 0x74;
  /** {@value #ineg_} */
  public static final String ineg_ = "ineg";
  /** {@value #LNEG} */
  public static final int LNEG = 0x75;
  /** {@value #lneg_} */
  public static final String lneg_ = "lneg";
  /** {@value #FNEG} */
  public static final int FNEG = 0x76;
  /** {@value #fneg_} */
  public static final String fneg_ = "fneg";
  /** {@value #DNEG} */
  public static final int DNEG = 0x77;
  /** {@value #dneg_} */
  public static final String dneg_ = "dneg";
  /** {@value #ISHL} */
  public static final int ISHL = 0x78;
  /** {@value #ishl_} */
  public static final String ishl_ = "ishl";
  /** {@value #LSHL} */
  public static final int LSHL = 0x79;
  /** {@value #lshl_} */
  public static final String lshl_ = "lshl";
  /** {@value #ISHR} */
  public static final int ISHR = 0x7A;
  /** {@value #ishr_} */
  public static final String ishr_ = "ishr";
  /** {@value #LSHR} */
  public static final int LSHR = 0x7B;
  /** {@value #lshr_} */
  public static final String lshr_ = "lshr";
  /** {@value #IUSHR} */
  public static final int IUSHR = 0x7C;
  /** {@value #iushr_} */
  public static final String iushr_ = "iushr";
  /** {@value #LUSHR} */
  public static final int LUSHR = 0x7D;
  /** {@value #lushr_} */
  public static final String lushr_ = "lushr";
  /** {@value #IAND} */
  public static final int IAND = 0x7E;
  /** {@value #iand_} */
  public static final String iand_ = "iand";
  /** {@value #LAND} */
  public static final int LAND = 0x7F;
  /** {@value #land_} */
  public static final String land_ = "land";
  /** {@value #IOR} */
  public static final int IOR = 0x80;
  /** {@value #ior_} */
  public static final String ior_ = "ior";
  /** {@value #LOR} */
  public static final int LOR = 0x81;
  /** {@value #lor_} */
  public static final String lor_ = "lor";
  /** {@value #IXOR} */
  public static final int IXOR = 0x82;
  /** {@value #ixor_} */
  public static final String ixor_ = "ixor";
  /** {@value #LXOR} */
  public static final int LXOR = 0x83;
  /** {@value #lxor_} */
  public static final String lxor_ = "lxor";
  /** {@value #IINC} */
  public static final int IINC = 0x84;
  /** {@value #iinc_} */
  public static final String iinc_ = "iinc";
  /** {@value #I2L} */
  public static final int I2L = 0x85;
  /** {@value #i2l_} */
  public static final String i2l_ = "i2l";
  /** {@value #I2F} */
  public static final int I2F = 0x86;
  /** {@value #i2f_} */
  public static final String i2f_ = "i2f";
  /** {@value #I2D} */
  public static final int I2D = 0x87;
  /** {@value #i2d_} */
  public static final String i2d_ = "i2d";
  /** {@value #L2I} */
  public static final int L2I = 0x88;
  /** {@value #l2i_} */
  public static final String l2i_ = "l2i";
  /** {@value #L2F} */
  public static final int L2F = 0x89;
  /** {@value #l2f_} */
  public static final String l2f_ = "l2f";
  /** {@value #L2D} */
  public static final int L2D = 0x8A;
  /** {@value #l2d_} */
  public static final String l2d_ = "l2d";
  /** {@value #F2I} */
  public static final int F2I = 0x8B;
  /** {@value #f2i_} */
  public static final String f2i_ = "f2i";
  /** {@value #F2L} */
  public static final int F2L = 0x8C;
  /** {@value #f2l_} */
  public static final String f2l_ = "f2l";
  /** {@value #F2D} */
  public static final int F2D = 0x8D;
  /** {@value #f2d_} */
  public static final String f2d_ = "f2d";
  /** {@value #D2I} */
  public static final int D2I = 0x8E;
  /** {@value #d2i_} */
  public static final String d2i_ = "d2i";
  /** {@value #D2L} */
  public static final int D2L = 0x8F;
  /** {@value #d2l_} */
  public static final String d2l_ = "d2l";
  /** {@value #D2F} */
  public static final int D2F = 0x90;
  /** {@value #d2f_} */
  public static final String d2f_ = "d2f";
  /** {@value #I2B} */
  public static final int I2B = 0x91;
  /** {@value #i2b_} */
  public static final String i2b_ = "i2b";
  /** {@value #I2C} */
  public static final int I2C = 0x92;
  /** {@value #i2c_} */
  public static final String i2c_ = "i2c";
  /** {@value #I2S} */
  public static final int I2S = 0x93;
  /** {@value #i2s_} */
  public static final String i2s_ = "i2s";
  /** {@value #LCMP} */
  public static final int LCMP = 0x94;
  /** {@value #lcmp_} */
  public static final String lcmp_ = "lcmp";
  /** {@value #FCMPL} */
  public static final int FCMPL = 0x95;
  /** {@value #fcmpl_} */
  public static final String fcmpl_ = "fcmpl";
  /** {@value #FCMPG} */
  public static final int FCMPG = 0x96;
  /** {@value #fcmpg_} */
  public static final String fcmpg_ = "fcmpg";
  /** {@value #DCMPL} */
  public static final int DCMPL = 0x97;
  /** {@value #dcmpl_} */
  public static final String dcmpl_ = "dcmpl";
  /** {@value #DCMPG} */
  public static final int DCMPG = 0x98;
  /** {@value #dcmpg_} */
  public static final String dcmpg_ = "dcmpg";
  /** {@value #IFEQ} */
  public static final int IFEQ = 0x99;
  /** {@value #ifeq_} */
  public static final String ifeq_ = "ifeq";
  /** {@value #IFNE} */
  public static final int IFNE = 0x9A;
  /** {@value #ifne_} */
  public static final String ifne_ = "ifne";
  /** {@value #IFLT} */
  public static final int IFLT = 0x9B;
  /** {@value #iflt_} */
  public static final String iflt_ = "iflt";
  /** {@value #IFGE} */
  public static final int IFGE = 0x9C;
  /** {@value #ifge_} */
  public static final String ifge_ = "ifge";
  /** {@value #IFGT} */
  public static final int IFGT = 0x9D;
  /** {@value #ifgt_} */
  public static final String ifgt_ = "ifgt";
  /** {@value #IFLE} */
  public static final int IFLE = 0x9E;
  /** {@value #ifle_} */
  public static final String ifle_ = "ifle";
  /** {@value #IF_ICMPEQ} */
  public static final int IF_ICMPEQ = 0x9F;
  /** {@value #if_icmpeq_} */
  public static final String if_icmpeq_ = "if_icmpeq";
  /** {@value #IF_ICMPNE} */
  public static final int IF_ICMPNE = 0xA0;
  /** {@value #if_icmpne_} */
  public static final String if_icmpne_ = "if_icmpne";
  /** {@value #IF_ICMPLT} */
  public static final int IF_ICMPLT = 0xA1;
  /** {@value #if_icmplt_} */
  public static final String if_icmplt_ = "if_icmplt";
  /** {@value #IF_ICMPGE} */
  public static final int IF_ICMPGE = 0xA2;
  /** {@value #if_icmpge_} */
  public static final String if_icmpge_ = "if_icmpge";
  /** {@value #IF_ICMPGT} */
  public static final int IF_ICMPGT = 0xA3;
  /** {@value #if_icmpgt_} */
  public static final String if_icmpgt_ = "if_icmpgt";
  /** {@value #IF_ICMPLE} */
  public static final int IF_ICMPLE = 0xA4;
  /** {@value #if_icmple_} */
  public static final String if_icmple_ = "if_icmple";
  /** {@value #IF_ACMPEQ} */
  public static final int IF_ACMPEQ = 0xA5;
  /** {@value #if_acmpeq_} */
  public static final String if_acmpeq_ = "if_acmpeq";
  /** {@value #IF_ACMPNE} */
  public static final int IF_ACMPNE = 0xA6;
  /** {@value #if_acmpne_} */
  public static final String if_acmpne_ = "if_acmpne";
  /** {@value #GOTO} */
  public static final int GOTO = 0xA7;
  /** {@value #goto_} */
  public static final String goto_ = "goto";
  /** {@value #JSR} */
  public static final int JSR = 0xA8;
  /** {@value #jsr_} */
  public static final String jsr_ = "jsr";
  /** {@value #RET} */
  public static final int RET = 0xA9;
  /** {@value #ret_} */
  public static final String ret_ = "ret";
  /** {@value #TABLESWITCH} */
  public static final int TABLESWITCH = 0xAA;
  /** {@value #tableswitch_} */
  public static final String tableswitch_ = "tableswitch";
  /** {@value #LOOKUPSWITCH} */
  public static final int LOOKUPSWITCH = 0xAB;
  /** {@value #lookupswitch_} */
  public static final String lookupswitch_ = "lookupswitch";
  /** {@value #IRETURN} */
  public static final int IRETURN = 0xAC;
  /** {@value #ireturn_} */
  public static final String ireturn_ = "ireturn";
  /** {@value #LRETURN} */
  public static final int LRETURN = 0xAD;
  /** {@value #lreturn_} */
  public static final String lreturn_ = "lreturn";
  /** {@value #FRETURN} */
  public static final int FRETURN = 0xAE;
  /** {@value #freturn_} */
  public static final String freturn_ = "freturn";
  /** {@value #DRETURN} */
  public static final int DRETURN = 0xAF;
  /** {@value #dreturn_} */
  public static final String dreturn_ = "dreturn";
  /** {@value #ARETURN} */
  public static final int ARETURN = 0xB0;
  /** {@value #areturn_} */
  public static final String areturn_ = "areturn";
  /** {@value #RETURN} */
  public static final int RETURN = 0xB1;
  /** {@value #return_} */
  public static final String return_ = "return";
  /** {@value #GETSTATIC} */
  public static final int GETSTATIC = 0xB2;
  /** {@value #getstatic_} */
  public static final String getstatic_ = "getstatic";
  /** {@value #PUTSTATIC} */
  public static final int PUTSTATIC = 0xB3;
  /** {@value #putstatic_} */
  public static final String putstatic_ = "putstatic";
  /** {@value #GETFIELD} */
  public static final int GETFIELD = 0xB4;
  /** {@value #getfield_} */
  public static final String getfield_ = "getfield";
  /** {@value #PUTFIELD} */
  public static final int PUTFIELD = 0xB5;
  /** {@value #putfield_} */
  public static final String putfield_ = "putfield";
  /** {@value #INVOKEVIRTUAL} */
  public static final int INVOKEVIRTUAL = 0xB6;
  /** {@value #invokevirtual_} */
  public static final String invokevirtual_ = "invokevirtual";
  /** {@value #INVOKESPECIAL} */
  public static final int INVOKESPECIAL = 0xB7;
  /** {@value #invokespecial_} */
  public static final String invokespecial_ = "invokespecial";
  /** {@value #INVOKESTATIC} */
  public static final int INVOKESTATIC = 0xB8;
  /** {@value #invokestatic_} */
  public static final String invokestatic_ = "invokestatic";
  /** {@value #INVOKEINTERFACE} */
  public static final int INVOKEINTERFACE = 0xB9;
  /** {@value #invokeinterface_} */
  public static final String invokeinterface_ = "invokeinterface";
  /** {@value #INVOKEDYNAMIC} */
  public static final int INVOKEDYNAMIC = 0xBA;
  /** {@value #invokedynamic_} */
  public static final String invokedynamic_ = "invokedynamic";
  /** {@value #NEW} */
  public static final int NEW = 0xBB;
  /** Konstan Object untuk {@code OpCode} */
  public static final String new_ = "new";
  /** {@value #NEWARRAY} */
  public static final int NEWARRAY = 0xBC;
  /** Konstan Object untuk {@code OpCode} */
  public static final String newarray_ = "newarray";
  /** {@value #ANEWARRAY} */
  public static final int ANEWARRAY = 0xBD;
  /** Konstan Object untuk {@code OpCode} */
  public static final String anewarray_ = "anewarray";
  /** {@value #ARRAYLENGTH} */
  public static final int ARRAYLENGTH = 0xBE;
  /** {@value #arraylength_} */
  public static final String arraylength_ = "arraylength";
  /** {@value #ATHROW} */
  public static final int ATHROW = 0xBF;
  /** {@value #athrow_} */
  public static final String athrow_ = "athrow";
  /** {@value #CHECKCAST} */
  public static final int CHECKCAST = 0xC0;
  /** {@value #checkcast_} */
  public static final String checkcast_ = "checkcast";
  /** {@value #INSTANCEOF} */
  public static final int INSTANCEOF = 0xC1;
  /** {@value #instanceof_} */
  public static final String instanceof_ = "instanceof";
  /** {@value #MONITORENTER} */
  public static final int MONITORENTER = 0xC2;
  /** {@value #monitorenter_} */
  public static final String monitorenter_ = "monitorenter";
  /** {@value #MONITOREXIT} */
  public static final int MONITOREXIT = 0xC3;
  /** {@value #monitorexit_} */
  public static final String monitorexit_ = "monitorexit";
  /** {@value #WIDE} */
  public static final int WIDE = 0xC4;
  /** {@value #wide_} */
  public static final String wide_ = "wide";
  /** {@value #MULTIANEWARRAY} */
  public static final int MULTIANEWARRAY = 0xC5;
  /** Konstan Object untuk {@code OpCode} */
  public static final String multianewarray_ = "multianewarray";
  /** {@value #IFNULL} */
  public static final int IFNULL = 0xC6;
  /** {@value #ifnull_} */
  public static final String ifnull_ = "ifnull";
  /** {@value #IFNONNULL} */
  public static final int IFNONNULL = 0xC7;
  /** {@value #ifnonnull_} */
  public static final String ifnonnull_ = "ifnonnull";
  /** {@value #GOTO_W} */
  public static final int GOTO_W = 0xC8;
  /** {@value #goto_w_} */
  public static final String goto_w_ = "goto_w";
  /** {@value #JSR_W} */
  public static final int JSR_W = 0xC9;
  /** {@value #jsr_w_} */
  public static final String jsr_w_ = "jsr_w";
  /** {@value #BREAKPOINT} */
  public static final int BREAKPOINT = 0xCA;
  /** {@value #breakpoint_} */
  public static final String breakpoint_ = "breakpoint";
  /** {@value #IMPDEP1} */
  public static final int IMPDEP1 = 0xFE;
  /** {@value #impdep1_} */
  public static final String impdep1_ = "impdep1";
  /** {@value #IMPDEP2} */
  public static final int IMPDEP2 = 0xFF;
  /** {@value #impdep2_} */
  public static final String impdep2_ = "impdep2";
  /** Konstan Object untuk {@code OpCode} */
  public static final OpCode Nop = new OpCode(nop_, NOP);
  /** Konstan Object untuk {@code OpCode} */
  public static final OpCode Aconst_null = new OpCode(aconst_null_, ACONST_NULL);
  /** Konstan Object untuk {@code OpCode} */
  public static final OpCode Iconst_m1 = new OpCode(iconst_m1_, ICONST_M1);
  /** Konstan Object untuk {@code OpCode} */
  public static final OpCode Iconst_0 = new OpCode(iconst_0_, ICONST_0);
  /** Konstan Object untuk {@code OpCode} */
  public static final OpCode Iconst_1 = new OpCode(iconst_1_, ICONST_1);
  /** Konstan Object untuk {@code OpCode} */
  public static final OpCode Iconst_2 = new OpCode(iconst_2_, ICONST_2);
  /** Konstan Object untuk {@code OpCode} */
  public static final OpCode Iconst_3 = new OpCode(iconst_3_, ICONST_3);
  /** Konstan Object untuk {@code OpCode} */
  public static final OpCode Iconst_4 = new OpCode(iconst_4_, ICONST_4);
  /** Konstan Object untuk {@code OpCode} */
  public static final OpCode Iconst_5 = new OpCode(iconst_5_, ICONST_5);
  /** Konstan Object untuk {@code OpCode} */
  public static final OpCode Lconst_0 = new OpCode(lconst_0_, LCONST_0);
  /** Konstan Object untuk {@code OpCode} */
  public static final OpCode Lconst_1 = new OpCode(lconst_1_, LCONST_1);
  /** Konstan Object untuk {@code OpCode} */
  public static final OpCode Fconst_0 = new OpCode(fconst_0_, FCONST_0);
  /** Konstan Object untuk {@code OpCode} */
  public static final OpCode Fconst_1 = new OpCode(fconst_1_, FCONST_1);
  /** Konstan Object untuk {@code OpCode} */
  public static final OpCode Fconst_2 = new OpCode(fconst_2_, FCONST_2);
  /** Konstan Object untuk {@code OpCode} */
  public static final OpCode Dconst_0 = new OpCode(dconst_0_, DCONST_0);
  /** Konstan Object untuk {@code OpCode} */
  public static final OpCode Dconst_1 = new OpCode(dconst_1_, DCONST_1);
  /** Konstan Object untuk {@code OpCode} */
  public static final OpCode Bipush = new OpCode(bipush_, BIPUSH);
  /** Konstan Object untuk {@code OpCode} */
  public static final OpCode Sipush = new OpCode(sipush_, SIPUSH);
  /** Konstan Object untuk {@code OpCode} */
  public static final OpCode Ldc = new OpCode(ldc_, LDC);
  /** Konstan Object untuk {@code OpCode} */
  public static final OpCode Ldc_w = new OpCode(ldc_w_, LDC_W);
  /** Konstan Object untuk {@code OpCode} */
  public static final OpCode Ldc2_w = new OpCode(ldc2_w_, LDC2_W);
  /** Konstan Object untuk {@code OpCode} */
  public static final OpCode Iload = new OpCode(iload_, ILOAD);
  /** Konstan Object untuk {@code OpCode} */
  public static final OpCode Lload = new OpCode(lload_, LLOAD);
  /** Konstan Object untuk {@code OpCode} */
  public static final OpCode Fload = new OpCode(fload_, FLOAD);
  /** Konstan Object untuk {@code OpCode} */
  public static final OpCode Dload = new OpCode(dload_, DLOAD);
  /** Konstan Object untuk {@code OpCode} */
  public static final OpCode Aload = new OpCode(aload_, ALOAD);
  /** Konstan Object untuk {@code OpCode} */
  public static final OpCode Iload_0 = new OpCode(iload_0_, ILOAD_0);
  /** Konstan Object untuk {@code OpCode} */
  public static final OpCode Iload_1 = new OpCode(iload_1_, ILOAD_1);
  /** Konstan Object untuk {@code OpCode} */
  public static final OpCode Iload_2 = new OpCode(iload_2_, ILOAD_2);
  /** Konstan Object untuk {@code OpCode} */
  public static final OpCode Iload_3 = new OpCode(iload_3_, ILOAD_3);
  /** Konstan Object untuk {@code OpCode} */
  public static final OpCode Lload_0 = new OpCode(lload_0_, LLOAD_0);
  /** Konstan Object untuk {@code OpCode} */
  public static final OpCode Lload_1 = new OpCode(lload_1_, LLOAD_1);
  /** Konstan Object untuk {@code OpCode} */
  public static final OpCode Lload_2 = new OpCode(lload_2_, LLOAD_2);
  /** Konstan Object untuk {@code OpCode} */
  public static final OpCode Lload_3 = new OpCode(lload_3_, LLOAD_3);
  /** Konstan Object untuk {@code OpCode} */
  public static final OpCode Fload_0 = new OpCode(fload_0_, FLOAD_0);
  /** Konstan Object untuk {@code OpCode} */
  public static final OpCode Fload_1 = new OpCode(fload_1_, FLOAD_1);
  /** Konstan Object untuk {@code OpCode} */
  public static final OpCode Fload_2 = new OpCode(fload_2_, FLOAD_2);
  /** Konstan Object untuk {@code OpCode} */
  public static final OpCode Fload_3 = new OpCode(fload_3_, FLOAD_3);
  /** Konstan Object untuk {@code OpCode} */
  public static final OpCode Dload_0 = new OpCode(dload_0_, DLOAD_0);
  /** Konstan Object untuk {@code OpCode} */
  public static final OpCode Dload_1 = new OpCode(dload_1_, DLOAD_1);
  /** Konstan Object untuk {@code OpCode} */
  public static final OpCode Dload_2 = new OpCode(dload_2_, DLOAD_2);
  /** Konstan Object untuk {@code OpCode} */
  public static final OpCode Dload_3 = new OpCode(dload_3_, DLOAD_3);
  /** Konstan Object untuk {@code OpCode} */
  public static final OpCode Aload_0 = new OpCode(aload_0_, ALOAD_0);
  /** Konstan Object untuk {@code OpCode} */
  public static final OpCode Aload_1 = new OpCode(aload_1_, ALOAD_1);
  /** Konstan Object untuk {@code OpCode} */
  public static final OpCode Aload_2 = new OpCode(aload_2_, ALOAD_2);
  /** Konstan Object untuk {@code OpCode} */
  public static final OpCode Aload_3 = new OpCode(aload_3_, ALOAD_3);
  /** Konstan Object untuk {@code OpCode} */
  public static final OpCode Iaload = new OpCode(iaload_, IALOAD);
  /** Konstan Object untuk {@code OpCode} */
  public static final OpCode Laload = new OpCode(laload_, LALOAD);
  /** Konstan Object untuk {@code OpCode} */
  public static final OpCode Faload = new OpCode(faload_, FALOAD);
  /** Konstan Object untuk {@code OpCode} */
  public static final OpCode Daload = new OpCode(daload_, DALOAD);
  /** Konstan Object untuk {@code OpCode} */
  public static final OpCode Aaload = new OpCode(aaload_, AALOAD);
  /** Konstan Object untuk {@code OpCode} */
  public static final OpCode Baload = new OpCode(baload_, BALOAD);
  /** Konstan Object untuk {@code OpCode} */
  public static final OpCode Caload = new OpCode(caload_, CALOAD);
  /** Konstan Object untuk {@code OpCode} */
  public static final OpCode Saload = new OpCode(saload_, SALOAD);
  /** Konstan Object untuk {@code OpCode} */
  public static final OpCode Istore = new OpCode(istore_, ISTORE);
  /** Konstan Object untuk {@code OpCode} */
  public static final OpCode Lstore = new OpCode(lstore_, LSTORE);
  /** Konstan Object untuk {@code OpCode} */
  public static final OpCode Fstore = new OpCode(fstore_, FSTORE);
  /** Konstan Object untuk {@code OpCode} */
  public static final OpCode Dstore = new OpCode(dstore_, DSTORE);
  /** Konstan Object untuk {@code OpCode} */
  public static final OpCode Astore = new OpCode(astore_, ASTORE);
  /** Konstan Object untuk {@code OpCode} */
  public static final OpCode Istore_0 = new OpCode(istore_0_, ISTORE_0);
  /** Konstan Object untuk {@code OpCode} */
  public static final OpCode Istore_1 = new OpCode(istore_1_, ISTORE_1);
  /** Konstan Object untuk {@code OpCode} */
  public static final OpCode Istore_2 = new OpCode(istore_2_, ISTORE_2);
  /** Konstan Object untuk {@code OpCode} */
  public static final OpCode Istore_3 = new OpCode(istore_3_, ISTORE_3);
  /** Konstan Object untuk {@code OpCode} */
  public static final OpCode Lstore_0 = new OpCode(lstore_0_, LSTORE_0);
  /** Konstan Object untuk {@code OpCode} */
  public static final OpCode Lstore_1 = new OpCode(lstore_1_, LSTORE_1);
  /** Konstan Object untuk {@code OpCode} */
  public static final OpCode Lstore_2 = new OpCode(lstore_2_, LSTORE_2);
  /** Konstan Object untuk {@code OpCode} */
  public static final OpCode Lstore_3 = new OpCode(lstore_3_, LSTORE_3);
  /** Konstan Object untuk {@code OpCode} */
  public static final OpCode Fstore_0 = new OpCode(fstore_0_, FSTORE_0);
  /** Konstan Object untuk {@code OpCode} */
  public static final OpCode Fstore_1 = new OpCode(fstore_1_, FSTORE_1);
  /** Konstan Object untuk {@code OpCode} */
  public static final OpCode Fstore_2 = new OpCode(fstore_2_, FSTORE_2);
  /** Konstan Object untuk {@code OpCode} */
  public static final OpCode Fstore_3 = new OpCode(fstore_3_, FSTORE_3);
  /** Konstan Object untuk {@code OpCode} */
  public static final OpCode Dstore_0 = new OpCode(dstore_0_, DSTORE_0);
  /** Konstan Object untuk {@code OpCode} */
  public static final OpCode Dstore_1 = new OpCode(dstore_1_, DSTORE_1);
  /** Konstan Object untuk {@code OpCode} */
  public static final OpCode Dstore_2 = new OpCode(dstore_2_, DSTORE_2);
  /** Konstan Object untuk {@code OpCode} */
  public static final OpCode Dstore_3 = new OpCode(dstore_3_, DSTORE_3);
  /** Konstan Object untuk {@code OpCode} */
  public static final OpCode Astore_0 = new OpCode(astore_0_, ASTORE_0);
  /** Konstan Object untuk {@code OpCode} */
  public static final OpCode Astore_1 = new OpCode(astore_1_, ASTORE_1);
  /** Konstan Object untuk {@code OpCode} */
  public static final OpCode Astore_2 = new OpCode(astore_2_, ASTORE_2);
  /** Konstan Object untuk {@code OpCode} */
  public static final OpCode Astore_3 = new OpCode(astore_3_, ASTORE_3);
  /** Konstan Object untuk {@code OpCode} */
  public static final OpCode Iastore = new OpCode(iastore_, IASTORE);
  /** Konstan Object untuk {@code OpCode} */
  public static final OpCode Lastore = new OpCode(lastore_, LASTORE);
  /** Konstan Object untuk {@code OpCode} */
  public static final OpCode Fastore = new OpCode(fastore_, FASTORE);
  /** Konstan Object untuk {@code OpCode} */
  public static final OpCode Dastore = new OpCode(dastore_, DASTORE);
  /** Konstan Object untuk {@code OpCode} */
  public static final OpCode Aastore = new OpCode(aastore_, AASTORE);
  /** Konstan Object untuk {@code OpCode} */
  public static final OpCode Bastore = new OpCode(bastore_, BASTORE);
  /** Konstan Object untuk {@code OpCode} */
  public static final OpCode Castore = new OpCode(castore_, CASTORE);
  /** Konstan Object untuk {@code OpCode} */
  public static final OpCode Sastore = new OpCode(sastore_, SASTORE);
  /** Konstan Object untuk {@code OpCode} */
  public static final OpCode Pop = new OpCode(pop_, POP);
  /** Konstan Object untuk {@code OpCode} */
  public static final OpCode Pop2 = new OpCode(pop2_, POP2);
  /** Konstan Object untuk {@code OpCode} */
  public static final OpCode Dup = new OpCode(dup_, DUP);
  /** Konstan Object untuk {@code OpCode} */
  public static final OpCode Dup_x1 = new OpCode(dup_x1_, DUP_X1);
  /** Konstan Object untuk {@code OpCode} */
  public static final OpCode Dup_x2 = new OpCode(dup_x2_, DUP_X2);
  /** Konstan Object untuk {@code OpCode} */
  public static final OpCode Dup2 = new OpCode(dup2_, DUP2);
  /** Konstan Object untuk {@code OpCode} */
  public static final OpCode Dup2_x1 = new OpCode(dup2_x1_, DUP2_X1);
  /** Konstan Object untuk {@code OpCode} */
  public static final OpCode Dup2_x2 = new OpCode(dup2_x2_, DUP2_X2);
  /** Konstan Object untuk {@code OpCode} */
  public static final OpCode Swap = new OpCode(swap_, SWAP);
  /** Konstan Object untuk {@code OpCode} */
  public static final OpCode Iadd = new OpCode(iadd_, IADD);
  /** Konstan Object untuk {@code OpCode} */
  public static final OpCode Ladd = new OpCode(ladd_, LADD);
  /** Konstan Object untuk {@code OpCode} */
  public static final OpCode Fadd = new OpCode(fadd_, FADD);
  /** Konstan Object untuk {@code OpCode} */
  public static final OpCode Dadd = new OpCode(dadd_, DADD);
  /** Konstan Object untuk {@code OpCode} */
  public static final OpCode Isub = new OpCode(isub_, ISUB);
  /** Konstan Object untuk {@code OpCode} */
  public static final OpCode Lsub = new OpCode(lsub_, LSUB);
  /** Konstan Object untuk {@code OpCode} */
  public static final OpCode Fsub = new OpCode(fsub_, FSUB);
  /** Konstan Object untuk {@code OpCode} */
  public static final OpCode Dsub = new OpCode(dsub_, DSUB);
  /** Konstan Object untuk {@code OpCode} */
  public static final OpCode Imul = new OpCode(imul_, IMUL);
  /** Konstan Object untuk {@code OpCode} */
  public static final OpCode Lmul = new OpCode(lmul_, LMUL);
  /** Konstan Object untuk {@code OpCode} */
  public static final OpCode Fmul = new OpCode(fmul_, FMUL);
  /** Konstan Object untuk {@code OpCode} */
  public static final OpCode Dmul = new OpCode(dmul_, DMUL);
  /** Konstan Object untuk {@code OpCode} */
  public static final OpCode Idiv = new OpCode(idiv_, IDIV);
  /** Konstan Object untuk {@code OpCode} */
  public static final OpCode Ldiv = new OpCode(ldiv_, LDIV);
  /** Konstan Object untuk {@code OpCode} */
  public static final OpCode Fdiv = new OpCode(fdiv_, FDIV);
  /** Konstan Object untuk {@code OpCode} */
  public static final OpCode Ddiv = new OpCode(ddiv_, DDIV);
  /** Konstan Object untuk {@code OpCode} */
  public static final OpCode Irem = new OpCode(irem_, IREM);
  /** Konstan Object untuk {@code OpCode} */
  public static final OpCode Lrem = new OpCode(lrem_, LREM);
  /** Konstan Object untuk {@code OpCode} */
  public static final OpCode Frem = new OpCode(frem_, FREM);
  /** Konstan Object untuk {@code OpCode} */
  public static final OpCode Drem = new OpCode(drem_, DREM);
  /** Konstan Object untuk {@code OpCode} */
  public static final OpCode Ineg = new OpCode(ineg_, INEG);
  /** Konstan Object untuk {@code OpCode} */
  public static final OpCode Lneg = new OpCode(lneg_, LNEG);
  /** Konstan Object untuk {@code OpCode} */
  public static final OpCode Fneg = new OpCode(fneg_, FNEG);
  /** Konstan Object untuk {@code OpCode} */
  public static final OpCode Dneg = new OpCode(dneg_, DNEG);
  /** Konstan Object untuk {@code OpCode} */
  public static final OpCode Ishl = new OpCode(ishl_, ISHL);
  /** Konstan Object untuk {@code OpCode} */
  public static final OpCode Lshl = new OpCode(lshl_, LSHL);
  /** Konstan Object untuk {@code OpCode} */
  public static final OpCode Ishr = new OpCode(ishr_, ISHR);
  /** Konstan Object untuk {@code OpCode} */
  public static final OpCode Lshr = new OpCode(lshr_, LSHR);
  /** Konstan Object untuk {@code OpCode} */
  public static final OpCode Iushr = new OpCode(iushr_, IUSHR);
  /** Konstan Object untuk {@code OpCode} */
  public static final OpCode Lushr = new OpCode(lushr_, LUSHR);
  /** Konstan Object untuk {@code OpCode} */
  public static final OpCode Iand = new OpCode(iand_, IAND);
  /** Konstan Object untuk {@code OpCode} */
  public static final OpCode Land = new OpCode(land_, LAND);
  /** Konstan Object untuk {@code OpCode} */
  public static final OpCode Ior = new OpCode(ior_, IOR);
  /** Konstan Object untuk {@code OpCode} */
  public static final OpCode Lor = new OpCode(lor_, LOR);
  /** Konstan Object untuk {@code OpCode} */
  public static final OpCode Ixor = new OpCode(ixor_, IXOR);
  /** Konstan Object untuk {@code OpCode} */
  public static final OpCode Lxor = new OpCode(lxor_, LXOR);
  /** Konstan Object untuk {@code OpCode} */
  public static final OpCode Iinc = new OpCode(iinc_, IINC);
  /** Konstan Object untuk {@code OpCode} */
  public static final OpCode I2l = new OpCode(i2l_, I2L);
  /** Konstan Object untuk {@code OpCode} */
  public static final OpCode I2f = new OpCode(i2f_, I2F);
  /** Konstan Object untuk {@code OpCode} */
  public static final OpCode I2d = new OpCode(i2d_, I2D);
  /** Konstan Object untuk {@code OpCode} */
  public static final OpCode L2i = new OpCode(l2i_, L2I);
  /** Konstan Object untuk {@code OpCode} */
  public static final OpCode L2f = new OpCode(l2f_, L2F);
  /** Konstan Object untuk {@code OpCode} */
  public static final OpCode L2d = new OpCode(l2d_, L2D);
  /** Konstan Object untuk {@code OpCode} */
  public static final OpCode F2i = new OpCode(f2i_, F2I);
  /** Konstan Object untuk {@code OpCode} */
  public static final OpCode F2l = new OpCode(f2l_, F2L);
  /** Konstan Object untuk {@code OpCode} */
  public static final OpCode F2d = new OpCode(f2d_, F2D);
  /** Konstan Object untuk {@code OpCode} */
  public static final OpCode D2i = new OpCode(d2i_, D2I);
  /** Konstan Object untuk {@code OpCode} */
  public static final OpCode D2l = new OpCode(d2l_, D2L);
  /** Konstan Object untuk {@code OpCode} */
  public static final OpCode D2f = new OpCode(d2f_, D2F);
  /** Konstan Object untuk {@code OpCode} */
  public static final OpCode I2b = new OpCode(i2b_, I2B);
  /** Konstan Object untuk {@code OpCode} */
  public static final OpCode I2c = new OpCode(i2c_, I2C);
  /** Konstan Object untuk {@code OpCode} */
  public static final OpCode I2s = new OpCode(i2s_, I2S);
  /** Konstan Object untuk {@code OpCode} */
  public static final OpCode Lcmp = new OpCode(lcmp_, LCMP);
  /** Konstan Object untuk {@code OpCode} */
  public static final OpCode Fcmpl = new OpCode(fcmpl_, FCMPL);
  /** Konstan Object untuk {@code OpCode} */
  public static final OpCode Fcmpg = new OpCode(fcmpg_, FCMPG);
  /** Konstan Object untuk {@code OpCode} */
  public static final OpCode Dcmpl = new OpCode(dcmpl_, DCMPL);
  /** Konstan Object untuk {@code OpCode} */
  public static final OpCode Dcmpg = new OpCode(dcmpg_, DCMPG);
  /** Konstan Object untuk {@code OpCode} */
  public static final OpCode Ifeq = new OpCode(ifeq_, IFEQ);
  /** Konstan Object untuk {@code OpCode} */
  public static final OpCode Ifne = new OpCode(ifne_, IFNE);
  /** Konstan Object untuk {@code OpCode} */
  public static final OpCode Iflt = new OpCode(iflt_, IFLT);
  /** Konstan Object untuk {@code OpCode} */
  public static final OpCode Ifge = new OpCode(ifge_, IFGE);
  /** Konstan Object untuk {@code OpCode} */
  public static final OpCode Ifgt = new OpCode(ifgt_, IFGT);
  /** Konstan Object untuk {@code OpCode} */
  public static final OpCode Ifle = new OpCode(ifle_, IFLE);
  /** Konstan Object untuk {@code OpCode} */
  public static final OpCode If_icmpeq = new OpCode(if_icmpeq_, IF_ICMPEQ);
  /** Konstan Object untuk {@code OpCode} */
  public static final OpCode If_icmpne = new OpCode(if_icmpne_, IF_ICMPNE);
  /** Konstan Object untuk {@code OpCode} */
  public static final OpCode If_icmplt = new OpCode(if_icmplt_, IF_ICMPLT);
  /** Konstan Object untuk {@code OpCode} */
  public static final OpCode If_icmpge = new OpCode(if_icmpge_, IF_ICMPGE);
  /** Konstan Object untuk {@code OpCode} */
  public static final OpCode If_icmpgt = new OpCode(if_icmpgt_, IF_ICMPGT);
  /** Konstan Object untuk {@code OpCode} */
  public static final OpCode If_icmple = new OpCode(if_icmple_, IF_ICMPLE);
  /** Konstan Object untuk {@code OpCode} */
  public static final OpCode If_acmpeq = new OpCode(if_acmpeq_, IF_ACMPEQ);
  /** Konstan Object untuk {@code OpCode} */
  public static final OpCode If_acmpne = new OpCode(if_acmpne_, IF_ACMPNE);
  /** Konstan Object untuk {@code OpCode} */
  public static final OpCode Goto = new OpCode(goto_, GOTO);
  /** Konstan Object untuk {@code OpCode} */
  public static final OpCode Jsr = new OpCode(jsr_, JSR);
  /** Konstan Object untuk {@code OpCode} */
  public static final OpCode Ret = new OpCode(ret_, RET);
  /** Konstan Object untuk {@code OpCode} */
  public static final OpCode Tableswitch = new OpCode(tableswitch_, TABLESWITCH);
  /** Konstan Object untuk {@code OpCode} */
  public static final OpCode Lookupswitch = new OpCode(lookupswitch_, LOOKUPSWITCH);
  /** Konstan Object untuk {@code OpCode} */
  public static final OpCode Ireturn = new OpCode(ireturn_, IRETURN);
  /** Konstan Object untuk {@code OpCode} */
  public static final OpCode Lreturn = new OpCode(lreturn_, LRETURN);
  /** Konstan Object untuk {@code OpCode} */
  public static final OpCode Freturn = new OpCode(freturn_, FRETURN);
  /** Konstan Object untuk {@code OpCode} */
  public static final OpCode Dreturn = new OpCode(dreturn_, DRETURN);
  /** Konstan Object untuk {@code OpCode} */
  public static final OpCode Areturn = new OpCode(areturn_, ARETURN);
  /** Konstan Object untuk {@code OpCode} */
  public static final OpCode Return = new OpCode(return_, RETURN);
  /** Konstan Object untuk {@code OpCode} */
  public static final OpCode Getstatic = new OpCode(getstatic_, GETSTATIC);
  /** Konstan Object untuk {@code OpCode} */
  public static final OpCode Putstatic = new OpCode(putstatic_, PUTSTATIC);
  /** Konstan Object untuk {@code OpCode} */
  public static final OpCode Getfield = new OpCode(getfield_, GETFIELD);
  /** Konstan Object untuk {@code OpCode} */
  public static final OpCode Putfield = new OpCode(putfield_, PUTFIELD);
  /** Konstan Object untuk {@code OpCode} */
  public static final OpCode Invokevirtual = new OpCode(invokevirtual_, INVOKEVIRTUAL);
  /** Konstan Object untuk {@code OpCode} */
  public static final OpCode Invokespecial = new OpCode(invokespecial_, INVOKESPECIAL);
  /** Konstan Object untuk {@code OpCode} */
  public static final OpCode Invokestatic = new OpCode(invokestatic_, INVOKESTATIC);
  /** Konstan Object untuk {@code OpCode} */
  public static final OpCode Invokeinterface = new OpCode(invokeinterface_, INVOKEINTERFACE);
  /** Konstan Object untuk {@code OpCode} */
  public static final OpCode Invokedynamic = new OpCode(invokedynamic_, INVOKEDYNAMIC);
  /** Konstan Object untuk {@code OpCode} */
  public static final OpCode New = new OpCode(new_, NEW);
  /** Konstan Object untuk {@code OpCode} */
  public static final OpCode Newarray = new OpCode(newarray_, NEWARRAY);
  /** Konstan Object untuk {@code OpCode} */
  public static final OpCode Anewarray = new OpCode(anewarray_, ANEWARRAY);
  /** Konstan Object untuk {@code OpCode} */
  public static final OpCode Arraylength = new OpCode(arraylength_, ARRAYLENGTH);
  /** Konstan Object untuk {@code OpCode} */
  public static final OpCode Athrow = new OpCode(athrow_, ATHROW);
  /** Konstan Object untuk {@code OpCode} */
  public static final OpCode Checkcast = new OpCode(checkcast_, CHECKCAST);
  /** Konstan Object untuk {@code OpCode} */
  public static final OpCode Instanceof = new OpCode(instanceof_, INSTANCEOF);
  /** Konstan Object untuk {@code OpCode} */
  public static final OpCode Monitorenter = new OpCode(monitorenter_, MONITORENTER);
  /** Konstan Object untuk {@code OpCode} */
  public static final OpCode Monitorexit = new OpCode(monitorexit_, MONITOREXIT);
  /** Konstan Object untuk {@code OpCode} */
  public static final OpCode Wide = new OpCode(wide_, WIDE);
  /** Konstan Object untuk {@code OpCode} */
  public static final OpCode Multianewarray = new OpCode(multianewarray_, MULTIANEWARRAY);
  /** Konstan Object untuk {@code OpCode} */
  public static final OpCode Ifnull = new OpCode(ifnull_, IFNULL);
  /** Konstan Object untuk {@code OpCode} */
  public static final OpCode Ifnonnull = new OpCode(ifnonnull_, IFNONNULL);
  /** Konstan Object untuk {@code OpCode} */
  public static final OpCode Goto_w = new OpCode(goto_w_, GOTO_W);
  /** Konstan Object untuk {@code OpCode} */
  public static final OpCode Jsr_w = new OpCode(jsr_w_, JSR_W);
  /** Konstan Object untuk {@code OpCode} */
  public static final OpCode Breakpoint = new OpCode(breakpoint_, BREAKPOINT);
  /** Konstan Object untuk {@code OpCode} */
  public static final OpCode Impdep1 = new OpCode(impdep1_, IMPDEP1);
  /** Konstan Object untuk {@code OpCode} */
  public static final OpCode Impdep2 = new OpCode(impdep2_, IMPDEP2);
  private String name;
  private int code;

  private OpCode(String name, int code){
    this.name=name;
    this.code=code;
  }
/** @return String getName() */
  public String getName() {
    return this.name;
  }
/** @return int getCode() */
  public int getCode() {
    return this.code;
  }

  private OpCode(){}
}
